NanoCount/NanoCount.py
NanoCount/Read.py
NanoCount/__init__.py
NanoCount/__main__.py
NanoCount/common.py
NanoCount-1.1.0.post2.dist-info/LICENSE
NanoCount-1.1.0.post2.dist-info/METADATA
NanoCount-1.1.0.post2.dist-info/WHEEL
NanoCount-1.1.0.post2.dist-info/entry_points.txt
NanoCount-1.1.0.post2.dist-info/top_level.txt
NanoCount-1.1.0.post2.dist-info/RECORD
