Metadata-Version: 2.1
Name: NanoCount
Version: 1.1.0.post2
Summary: NanoCount estimates transcripts abundance from Oxford Nanopore *direct-RNA sequencing* datasets, using an expectation-maximization approach like RSEM, Kallisto, salmon, etc to handle the uncertainty of multi-mapping reads
Home-page: https://github.com/a-slide/NanoCount/
Author: Adrien Leger
Author-email: aleg@ebi.ac.uk
License: MIT
Classifier: Development Status :: 3 - Alpha
Classifier: Intended Audience :: Science/Research
Classifier: Topic :: Scientific/Engineering :: Bio-Informatics
Classifier: License :: OSI Approved :: MIT License
Classifier: Programming Language :: Python :: 3
Requires-Python: >=3.6
License-File: LICENSE
Requires-Dist: tqdm >=4.51.0
Requires-Dist: numpy >=1.19.4
Requires-Dist: pysam >=0.16.0
Requires-Dist: pandas >=1.1.4
Requires-Dist: colorlog >=4.1.0
